dict2cypher.py
dict2cypher-23.dist-info/METADATA
dict2cypher-23.dist-info/WHEEL
dict2cypher-23.dist-info/top_level.txt
dict2cypher-23.dist-info/RECORD
