Metadata-Version: 2.4
Name: dict2cypher
Version: 23
Summary: Convert Python dicts to Neo4j Cypher queries easily
Author: Norman Koch
Author-email: Norman Koch <norman.koch@tu-dresden.de>
License: GPL-3.0-or-later
Requires-Python: >=3.9
Dynamic: author
Dynamic: requires-python
